book_records/__init__.py
book_records/main.py
book_records_app-1.0.0.dist-info/METADATA
book_records_app-1.0.0.dist-info/WHEEL
book_records_app-1.0.0.dist-info/entry_points.txt
book_records_app-1.0.0.dist-info/top_level.txt
book_records_app-1.0.0.dist-info/RECORD
